utils/__init__.py
utils/admin.py
utils/apps.py
utils/models.py
utils/tests.py
utils/views.py
utils/migrations/__init__.py
utils_django-0.0.3.dist-info/METADATA
utils_django-0.0.3.dist-info/WHEEL
utils_django-0.0.3.dist-info/top_level.txt
utils_django-0.0.3.dist-info/RECORD
